QStyler/__init__.py
QStyler/__main__.py
QStyler/collectionsTab.py
QStyler/dialog.py
QStyler/editorTab.py
QStyler/menubar.py
QStyler/styler.py
QStyler/utils.py
QStyler/version.py
QStyler/widgets.py
QStyler/window.py
QStyler/data/data.json
QStyler/icons/QStylerIcon.png
QStyler/icons/add.png
QStyler/icons/checked.png
QStyler/icons/confirm.png
QStyler/icons/down-arrow.png
QStyler/icons/export.png
QStyler/icons/extend-left.png
QStyler/icons/extend-right.png
QStyler/icons/github.png
QStyler/icons/import.png
QStyler/icons/live.png
QStyler/icons/minus.png
QStyler/icons/next-page.png
QStyler/icons/plus.png
QStyler/icons/preview.png
QStyler/icons/question.png
QStyler/icons/rename.png
QStyler/icons/reset.png
QStyler/icons/save.png
QStyler/icons/trash.png
QStyler/icons/up-arrow.png
QStyler/themes/Bland.json
QStyler/themes/Coastal.json
QStyler/themes/DarkSkyline.json
QStyler/themes/KnightRider.json
QStyler/themes/MaterialDarkStyle.json
QStyler/themes/Mellenium.json
QStyler/themes/MintyMixup.json
QStyler/themes/NeonButtons.json
QStyler/themes/NightLights.json
QStyler/themes/OSX.json
QStyler/themes/Overcast.json
QStyler/themes/PurpleGrape.json
QStyler/themes/SummerBreeze.json
QStyler/themes/Terminal.json
QStyler/themes/Ubuntu.json
QStyler-0.1.8.dist-info/LICENSE
QStyler-0.1.8.dist-info/METADATA
QStyler-0.1.8.dist-info/WHEEL
QStyler-0.1.8.dist-info/entry_points.txt
QStyler-0.1.8.dist-info/top_level.txt
QStyler-0.1.8.dist-info/RECORD
