Metadata-Version: 2.1
Name: QStyler
Version: 0.1.8
Summary: QStyleSheet testing application.
Home-page: https://github.com/alexpdev/qstyler
Author: alexpdev
Author-email: alexpdev <alexpdev@pm.me>
License: Apache License
Keywords: Qt,GUI,QStyleSheet,qss
Classifier: Development Status :: 4 - Beta
Classifier: Intended Audience :: Developers
Classifier: License :: OSI Approved :: Apache Software License
Classifier: Operating System :: OS Independent
Classifier: Programming Language :: Python :: 3.5
Classifier: Programming Language :: Python :: 3.6
Classifier: Programming Language :: Python :: 3.7
Classifier: Programming Language :: Python :: 3.8
Classifier: Programming Language :: Python :: 3.9
Classifier: Programming Language :: Python :: 3.10
Classifier: Programming Language :: Python :: 3.11
Requires-Python: >=3.6
License-File: LICENSE
Requires-Dist: PySide6
Requires-Dist: wheel
